starcraft_data_orm/__init__.py
starcraft_data_orm/exceptions.py
starcraft_data_orm/inject/Injectable.py
starcraft_data_orm/inject/__init__.py
starcraft_data_orm/warehouse/__init__.py
starcraft_data_orm/warehouse/base.py
starcraft_data_orm/warehouse/config.py
starcraft_data_orm/warehouse/datapack/__init__.py
starcraft_data_orm/warehouse/datapack/ability.py
starcraft_data_orm/warehouse/datapack/unit_type.py
starcraft_data_orm/warehouse/events/__init__.py
starcraft_data_orm/warehouse/events/basic_command_event.py
starcraft_data_orm/warehouse/events/chat_event.py
starcraft_data_orm/warehouse/events/player_leave_event.py
starcraft_data_orm/warehouse/events/player_stats_event.py
starcraft_data_orm/warehouse/events/unit_born_event.py
starcraft_data_orm/warehouse/events/unit_died_event.py
starcraft_data_orm/warehouse/events/unit_done_event.py
starcraft_data_orm/warehouse/events/unit_init_event.py
starcraft_data_orm/warehouse/events/upgrade_complete_event.py
starcraft_data_orm/warehouse/replay/__init__.py
starcraft_data_orm/warehouse/replay/info.py
starcraft_data_orm/warehouse/replay/map.py
starcraft_data_orm/warehouse/replay/object.py
starcraft_data_orm/warehouse/replay/player.py
starcraft_data_orm/warehouse/replay/user.py
tests/__init__.py
tests/test_warehouse/__init__.py
tests/test_warehouse/test_datapack/__init__.py
tests/test_warehouse/test_datapack/ability_factory.py
tests/test_warehouse/test_datapack/test_ability.py
tests/test_warehouse/test_datapack/test_unit_type.py
tests/test_warehouse/test_datapack/unit_type_factory.py
starcraft_data_orm-0.1.7.dist-info/METADATA
starcraft_data_orm-0.1.7.dist-info/WHEEL
starcraft_data_orm-0.1.7.dist-info/top_level.txt
starcraft_data_orm-0.1.7.dist-info/RECORD
