Metadata-Version: 2.2
Name: starcraft-data-orm
Version: 0.1.7
Summary: A Python package for StarCraft replay data ORM integration.
Home-page: https://github.com/OpenJ92/starcraft-data-orm
Author: Jacob Vartuli-Schonberg
Author-email: jacob.vartuli.schonberg@gmail.com
License: MIT
Classifier: Programming Language :: Python :: 3
Classifier: License :: OSI Approved :: MIT License
Classifier: Operating System :: OS Independent
Requires-Python: >=3.9
Requires-Dist: async-timeout==5.0.1
Requires-Dist: asyncpg==0.30.0
Requires-Dist: boto3==1.35.90
Requires-Dist: botocore==1.35.90
Requires-Dist: build==1.2.2.post1
Requires-Dist: coverage==7.6.10
Requires-Dist: exceptiongroup==1.2.2
Requires-Dist: factory_boy==3.3.1
Requires-Dist: Faker==33.3.0
Requires-Dist: greenlet==3.1.1
Requires-Dist: importlib_metadata==8.5.0
Requires-Dist: iniconfig==2.0.0
Requires-Dist: jmespath==1.0.1
Requires-Dist: mpyq==0.2.5
Requires-Dist: packaging==24.2
Requires-Dist: pluggy==1.5.0
Requires-Dist: psycopg2==2.9.10
Requires-Dist: pyproject_hooks==1.2.0
Requires-Dist: pytest==8.3.4
Requires-Dist: pytest-asyncio==0.25.1
Requires-Dist: pytest-cov==6.0.0
Requires-Dist: python-dateutil==2.9.0.post0
Requires-Dist: s3transfer==0.10.4
Requires-Dist: sc2reader==1.8.0
Requires-Dist: six==1.17.0
Requires-Dist: SQLAlchemy==2.0.36
Requires-Dist: storage-bridge==0.1.2
Requires-Dist: tomli==2.2.1
Requires-Dist: typing_extensions==4.12.2
Requires-Dist: urllib3==1.26.20
Requires-Dist: zipp==3.21.0
Dynamic: author
Dynamic: author-email
Dynamic: classifier
Dynamic: description
Dynamic: description-content-type
Dynamic: home-page
Dynamic: license
Dynamic: requires-dist
Dynamic: requires-python
Dynamic: summary
